awscli_login/__init__.py
awscli_login/__main__.py
awscli_login/account_names.py
awscli_login/config.py
awscli_login/configure.py
awscli_login/const.py
awscli_login/exceptions.py
awscli_login/logger.py
awscli_login/saml.py
awscli_login/typing.py
awscli_login/util.py
tests/__init__.py
tests/base.py
tests/exceptions.py
tests/test_configure.py
tests/test_saml.py
tests/test_util.py
tests/util.py
tests/cli/__init__.py
tests/cli/test_logout.py
tests/config/__init__.py
tests/config/base.py
tests/config/test_factor.py
tests/config/test_get_credentials.py
tests/config/test_profile.py
tests/config/test_update.py
tests/config/util.py
co_awscli_login-0.1.0a8.dist-info/LICENSE
co_awscli_login-0.1.0a8.dist-info/METADATA
co_awscli_login-0.1.0a8.dist-info/WHEEL
co_awscli_login-0.1.0a8.dist-info/top_level.txt
co_awscli_login-0.1.0a8.dist-info/RECORD
