Metadata-Version: 2.1
Name: co-awscli-login
Version: 0.1.0a8
Summary: Plugin for the AWS CLI that retrieves and rotates credentials using SAML ECP and STS.
Home-page: https://github.com/techservicesillinois/awscli-login
Author: David D. Riddle
Author-email: ddriddle@illinois.edu
License: UNKNOWN
Project-URL: Bug Reports, https://github.com/techservicesillinois/awscli-login/issues
Project-URL: Source, https://github.com/techservicesillinois/awscli-login
Keywords: Amazon AWS SAML login access keys
Platform: UNKNOWN
Classifier: Development Status :: 3 - Alpha
Classifier: Environment :: Console
Classifier: Intended Audience :: Developers
Classifier: Intended Audience :: System Administrators
Classifier: License :: OSI Approved :: MIT License
Classifier: Natural Language :: English
Classifier: Programming Language :: Python :: 3.5
Classifier: Programming Language :: Python :: 3.6
Requires-Python: >=3.5
Requires-Dist: awscli
Requires-Dist: boto3
Requires-Dist: botocore
Requires-Dist: daemoniker
Requires-Dist: keyring
Requires-Dist: lxml
Requires-Dist: psutil
Requires-Dist: requests
Provides-Extra: test
Requires-Dist: Sphinx ; extra == 'test'
Requires-Dist: coverage ; extra == 'test'
Requires-Dist: sphinx-autodoc-typehints ; extra == 'test'
Requires-Dist: sphinx-rtd-theme ; extra == 'test'
Requires-Dist: tblib ; extra == 'test'
Requires-Dist: tox ; extra == 'test'
Requires-Dist: tox-pyenv ; extra == 'test'
Requires-Dist: wurlitzer ; extra == 'test'
